mediapipe/__init__.py
mediapipe/python/solution_base.py
mediapipe/python/_framework_bindings.cpython-39-x86_64-linux-gnu.so
mediapipe/python/solution_base_test.py
mediapipe/python/packet_creator.py
mediapipe/python/__init__.py
mediapipe/python/image_test.py
mediapipe/python/calculator_graph_test.py
mediapipe/python/packet_getter.py
mediapipe/python/image_frame_test.py
mediapipe/python/timestamp_test.py
mediapipe/python/packet_test.py
mediapipe/python/solutions/drawing_utils.py
mediapipe/python/solutions/objectron_test.py
mediapipe/python/solutions/face_detection_test.py
mediapipe/python/solutions/pose.py
mediapipe/python/solutions/selfie_segmentation_test.py
mediapipe/python/solutions/hands_test.py
mediapipe/python/solutions/objectron.py
mediapipe/python/solutions/selfie_segmentation.py
mediapipe/python/solutions/face_mesh.py
mediapipe/python/solutions/__init__.py
mediapipe/python/solutions/pose_connections.py
mediapipe/python/solutions/pose_test.py
mediapipe/python/solutions/face_mesh_connections.py
mediapipe/python/solutions/face_mesh_test.py
mediapipe/python/solutions/hands_connections.py
mediapipe/python/solutions/drawing_utils_test.py
mediapipe/python/solutions/drawing_styles.py
mediapipe/python/solutions/hands.py
mediapipe/python/solutions/face_detection.py
mediapipe/python/solutions/holistic_test.py
mediapipe/python/solutions/holistic.py
mediapipe/python/solutions/download_utils.py
mediapipe/calculators/__init__.py
mediapipe/calculators/image/set_alpha_calculator_pb2.py
mediapipe/calculators/image/segmentation_smoothing_calculator_pb2.py
mediapipe/calculators/image/feature_detector_calculator_pb2.py
mediapipe/calculators/image/image_clone_calculator_pb2.py
mediapipe/calculators/image/__init__.py
mediapipe/calculators/image/mask_overlay_calculator_pb2.py
mediapipe/calculators/image/image_transformation_calculator_pb2.py
mediapipe/calculators/image/opencv_image_encoder_calculator_pb2.py
mediapipe_nightly-0.10.22.post20250228.dist-info/RECORD
mediapipe_nightly-0.10.22.post20250228.dist-info/METADATA
mediapipe_nightly-0.10.22.post20250228.dist-info/LICENSE
mediapipe_nightly-0.10.22.post20250228.dist-info/WHEEL
mediapipe_nightly-0.10.22.post20250228.dist-info/top_level.txt
